cached_property/__init__.py
cached_property/cached_property.py
cached_property/test_cached_property.py
cached_property_bel-1.0.1.dist-info/LICENSE
cached_property_bel-1.0.1.dist-info/METADATA
cached_property_bel-1.0.1.dist-info/WHEEL
cached_property_bel-1.0.1.dist-info/top_level.txt
cached_property_bel-1.0.1.dist-info/RECORD
