Metadata-Version: 2.1
Name: cached-property-bel
Version: 1.0.1
Summary: A cached-property decorator.
Home-page: UNKNOWN
Author: Justus Schwabedal
Author-email: jschwabedal@belco.tech
Maintainer: Justus Schwabedal
Maintainer-email: jschwabedal@belco.tech
License: UNKNOWN
Platform: UNKNOWN
Classifier: Programming Language :: Python :: 3
Classifier: License :: OSI Approved :: Apache Software License
Classifier: Operating System :: OS Independent
Requires-Python: >=3.6
